pyslurmtq/SLURMTaskQueue.py
pyslurmtq/Slot.py
pyslurmtq/Task.py
pyslurmtq/__init__.py
pyslurmtq/pyslurmtq.py
pyslurmtq/utils.py
pyslurmtq-0.0.2.dist-info/LICENSE.txt
pyslurmtq-0.0.2.dist-info/METADATA
pyslurmtq-0.0.2.dist-info/WHEEL
pyslurmtq-0.0.2.dist-info/entry_points.txt
pyslurmtq-0.0.2.dist-info/top_level.txt
pyslurmtq-0.0.2.dist-info/RECORD
