Metadata-Version: 2.1
Name: pyslurmtq
Version: 0.0.2
Summary: Add a short description here!
Home-page: https://github.com/pyscaffold/pyscaffold/
Author: Carlos del-Castillo-Negrete
Author-email: cdelcastillo21@gmail.com
License: MIT
Project-URL: Source, https://github.com/cdelcastillo21/pyslurmtq
Project-URL: Tracker, https://github.com/cdelcastillo21/pyslurmtq/issues
Platform: any
Classifier: Development Status :: 4 - Beta
Classifier: Programming Language :: Python
Requires-Python: >=3.8
License-File: LICENSE.txt
Requires-Dist: python-json-logger
Requires-Dist: prettytable
Requires-Dist: importlib-metadata ; python_version >= "3.8"
Provides-Extra: testing
Requires-Dist: setuptools ; extra == 'testing'
Requires-Dist: pytest ; extra == 'testing'
Requires-Dist: pytest-cov ; extra == 'testing'
